setup.py
adapt/__init__.py
adapt/context.py
adapt/engine.py
adapt/entity_tagger.py
adapt/expander.py
adapt/intent.py
adapt/parser.py
adapt/tools/__init__.py
adapt/tools/text/__init__.py
adapt/tools/text/tokenizer.py
adapt/tools/text/trie.py
onyx_parser.egg-info/PKG-INFO
onyx_parser.egg-info/SOURCES.txt
onyx_parser.egg-info/dependency_links.txt
onyx_parser.egg-info/requires.txt
onyx_parser.egg-info/top_level.txt