Metadata-Version: 1.0
Name: onyx-parser
Version: 0.3.0
Summary: A text-to-intent parsing framework.
Home-page: https://github.com/OnyxProject/adapt
Author: Sean Fitzgerald
Author-email: sean@fitzgeralds.me
License: LGPL-3
Keywords: natural language processing
Platform: UNKNOWN
